{
  "swagger": "2.0",
  "info": {
    "version": "1.0.0",
    "title": "Motors shop",
    "description": "REST API to manager a vehicles e-commerce."
  },
  "host": "localhost:3000",
  "basePath": "/",
  "schemes": ["http"],
  "paths": {
    "announcement/{id}": {
      "delete": {
        "description": "",
        "parameters": [
          {
            "name": "id",
            "in": "path",
            "required": true,
            "type": "string"
          }
        ],
        "responses": {
          "204": {
            "description": "No Content"
          }
        }
      },
      "get": {
        "description": "",
        "parameters": [
          {
            "name": "id",
            "in": "path",
            "required": true,
            "type": "string"
          }
        ],
        "responses": {
          "200": {
            "description": "OK"
          },
          "400": {
            "description": "Bad Request"
          }
        }
      },
      "patch": {
        "description": "",
        "parameters": [
          {
            "name": "id",
            "in": "path",
            "required": true,
            "type": "string"
          }
        ],
        "responses": {
          "200": {
            "description": "OK"
          },
          "400": {
            "description": "Bad Request"
          }
        }
      }
    }
  }
}
